README.txt
setup.py
Pybles.egg-info/PKG-INFO
Pybles.egg-info/SOURCES.txt
Pybles.egg-info/dependency_links.txt
Pybles.egg-info/requires.txt
Pybles.egg-info/top_level.txt
pybles/__init__.py
pybles/colors.py
pybles/pybles.py
pybles/test.py