Metadata-Version: 1.1
Name: Pybles
Version: 1.0.13
Summary: Module to represent tables in the terminal using python
Home-page: http://pypi.python.org/pypi/Pybles/
Author: Guido Accardo
Author-email: gaccardo@gmail.com
License: GPLv2
Keywords: ssh networking console tools
Platform: UNKNOWN
Classifier: Operating System :: OS Independent
Classifier: Programming Language :: Python :: 2.7
Classifier: Topic :: System :: Systems Administration
Classifier: Topic :: System :: Networking
Classifier: Topic :: Utilities
Classifier: Topic :: Terminals
Classifier: Environment :: Console
Classifier: License :: OSI Approved :: GNU General Public License (GPL)
